pipethon/__init__.py
pipethon-1.0.3.dist-info/METADATA
pipethon-1.0.3.dist-info/WHEEL
pipethon-1.0.3.dist-info/top_level.txt
pipethon-1.0.3.dist-info/RECORD
